dep_graph_vh/__init__.py
dep_graph_vh/__main__.py
dep_graph_vh/exceptions.py
dep_graph_vh/reader.py
dep_graph_vh/resolver.py
dep_graph_vh/visualizer.py
dep_graph_vh-1.0.0.dist-info/LICENSE
dep_graph_vh-1.0.0.dist-info/METADATA
dep_graph_vh-1.0.0.dist-info/WHEEL
dep_graph_vh-1.0.0.dist-info/top_level.txt
dep_graph_vh-1.0.0.dist-info/RECORD
