Metadata-Version: 2.1
Name: dep-graph-vh
Version: 1.0.0
Summary: Simple dependency graph resolver with JSON input
Author-email: Viktor Hyhyniak <hyhyniak.victor@gmail.com>
License: MIT License
Project-URL: repository, https://gitlab.com/hyhyniak.victor/dep_graph
Classifier: Programming Language :: Python :: 3
Classifier: License :: OSI Approved :: MIT License
Classifier: Operating System :: OS Independent
Requires-Python: >=3.11
License-File: LICENSE
